OAuthWb/OAuthWb.py
OAuthWb/WB_tool.py
OAuthWb/__init__.py
OAuthWb-0.0.7.dist-info/LICENSE
OAuthWb-0.0.7.dist-info/METADATA
OAuthWb-0.0.7.dist-info/WHEEL
OAuthWb-0.0.7.dist-info/top_level.txt
OAuthWb-0.0.7.dist-info/RECORD
