Metadata-Version: 2.1
Name: OAuthWb
Version: 0.0.7
Summary: weibo_login
Home-page: https://github.com/yinbohang/weibo_login
Author: DAHANGZAIYA
Author-email: y17505251998@163.com
License: MIT
Platform: UNKNOWN
Classifier: Programming Language :: Python :: 3
Classifier: License :: OSI Approved :: MIT License
Classifier: Operating System :: OS Independent
Requires-Python: >=3.0
